pocketbase_connection.py
pocketbase_connection-0.2.0.dist-info/LICENSE
pocketbase_connection-0.2.0.dist-info/METADATA
pocketbase_connection-0.2.0.dist-info/WHEEL
pocketbase_connection-0.2.0.dist-info/RECORD
