Metadata-Version: 2.1
Name: pocketbase-connection
Version: 0.2.0
Summary: Streamlit extension to access pocketbase
Home-page: https://github.com/Ashwin-op/pocketbase-connection
License: MIT
Author: Ashwin
Author-email: bsashwin9@gmail.com
Requires-Python: >=3.10,<4.0
Classifier: License :: OSI Approved :: MIT License
Classifier: Programming Language :: Python :: 3
Classifier: Programming Language :: Python :: 3.10
Classifier: Programming Language :: Python :: 3.11
Classifier: Programming Language :: Python :: 3.12
Requires-Dist: pocketbase (>=0.9.2,<0.10.0)
Requires-Dist: streamlit (>=1.29.0,<2.0.0)
